Workbook

Sheet START HERE
A1: Financial Statement Analysis
A2: Generated by edgar-query. The Financial Data sheet is already filled from SEC EDGAR; every other sheet is live formulas.
A5: What you are building
A6: One company. Five fiscal years. Statements, common-size, trend and ratios are all filled in and linked - every analysis cell is a live formula pointing at Financial Data.
A8: Colour code
A9: Yellow cells = you type the number in.
A10: Green cells = you write the formula.
A13: The sheets, in order
A14: Financial Data - Filled from SEC EDGAR. Every other sheet links back to it.
A15: Common-Size - Every income statement line as a % of Revenue. Every balance sheet line as a % of Total Assets.
A16: Trend - Percent change from one year to the next, plus an indexed view with your earliest year as the base.
A17: Ratios - Fifteen ratios plus the DuPont decomposition.
... A43: [ ] You have not left the TTM column in by mistake

Sheet Financial Data
A1: Financial Data - type your five years here
A2: This is the only sheet where you type numbers. Everything else links back to it.
A3: Company name | I3: Oldest year on the left, most recent on the right. Keep that order everywhere.
A4: Ticker symbol
A5: Units (e.g. millions USD)
A6: Data source (paste the URL)
A8: Fiscal Year
A9: INCOME STATEMENT
A10: Revenue (Net Sales)
A11: Cost of Revenue (COGS)
A12: Gross Profit
A13: Operating Expenses
A14: Operating Income (EBIT)
A15: Interest Expense
A16: Pretax Income
... A39: Total Shareholders' Equity
A41: CHECK: Assets - (Liabilities + Equity) | C41: =IF(COUNT(C29,C38,C39)<3,"",C29-(C38+C39)) | D41: =IF(COUNT(D29,D38,D39)<3,"",D29-(D38+D39)) | E41: =IF(COUNT(E29,E38,E39)<3,"",E29-(E38+E39)) | F41: =IF(COUNT(F29,F38,F39)<3,"",F29-(F38+F39)) | G41: =IF(COUNT(G29,G38,G39)<3,"",G29-(G38+G39)) | I41: Should be within about 1.0 of zero in every year. Published figures are rounded, so a few tenths is normal. A number in the tens or hundreds means a typo above, or a line item you left out.

Sheet Common-Size
A1: Common-Size Statements
A2: Income statement as a % of Revenue. Balance sheet as a % of Total Assets.
A8: Fiscal Year | C8: ='Financial Data'!C8 | D8: ='Financial Data'!D8 | E8: ='Financial Data'!E8 | F8: ='Financial Data'!F8 | G8: ='Financial Data'!G8
A9: INCOME STATEMENT | I9: Divide each income statement line by that year's Revenue. Lock the Revenue row with $ so you can drag the formula down: ='Financial Data'!C10/'Financial Data'!C$10
A10: Revenue (Net Sales) | C10: ='Financial Data'!C10/'Financial Data'!C$10 | D10: ='Financial Data'!D10/'Financial Data'!D$10 | E10: ='Financial Data'!E10/'Financial Data'!E$10 | F10: ='Financial Data'!F10/'Financial Data'!F$10 | G10: ='Financial Data'!G10/'Financial Data'!G$10
A11: Cost of Revenue (COGS) | C11: ='Financial Data'!C11/'Financial Data'!C$10 | D11: ='Financial Data'!D11/'Financial Data'!D$10 | E11: ='Financial Data'!E11/'Financial Data'!E$10 | F11: ='Financial Data'!F11/'Financial Data'!F$10 | G11: ='Financial Data'!G11/'Financial Data'!G$10
A12: Gross Profit | C12: ='Financial Data'!C12/'Financial Data'!C$10 | D12: ='Financial Data'!D12/'Financial Data'!D$10 | E12: ='Financial Data'!E12/'Financial Data'!E$10 | F12: ='Financial Data'!F12/'Financial Data'!F$10 | G12: ='Financial Data'!G12/'Financial Data'!G$10
A13: Operating Expenses | C13: ='Financial Data'!C13/'Financial Data'!C$10 | D13: ='Financial Data'!D13/'Financial Data'!D$10 | E13: ='Financial Data'!E13/'Financial Data'!E$10 | F13: ='Financial Data'!F13/'Financial Data'!F$10 | G13: ='Financial Data'!G13/'Financial Data'!G$10
A14: Operating Income (EBIT) | C14: ='Financial Data'!C14/'Financial Data'!C$10 | D14: ='Financial Data'!D14/'Financial Data'!D$10 | E14: ='Financial Data'!E14/'Financial Data'!E$10 | F14: ='Financial Data'!F14/'Financial Data'!F$10 | G14: ='Financial Data'!G14/'Financial Data'!G$10
A15: Interest Expense | C15: ='Financial Data'!C15/'Financial Data'!C$10 | D15: ='Financial Data'!D15/'Financial Data'!D$10 | E15: ='Financial Data'!E15/'Financial Data'!E$10 | F15: ='Financial Data'!F15/'Financial Data'!F$10 | G15: ='Financial Data'!G15/'Financial Data'!G$10
A16: Pretax Income | C16: ='Financial Data'!C16/'Financial Data'!C$10 | D16: ='Financial Data'!D16/'Financial Data'!D$10 | E16: ='Financial Data'!E16/'Financial Data'!E$10 | F16: ='Financial Data'!F16/'Financial Data'!F$10 | G16: ='Financial Data'!G16/'Financial Data'!G$10
A17: Income Tax Expense | C17: ='Financial Data'!C17/'Financial Data'!C$10 | D17: ='Financial Data'!D17/'Financial Data'!D$10 | E17: ='Financial Data'!E17/'Financial Data'!E$10 | F17: ='Financial Data'!F17/'Financial Data'!F$10 | G17: ='Financial Data'!G17/'Financial Data'!G$10
A18: Net Income | C18: ='Financial Data'!C18/'Financial Data'!C$10 | D18: ='Financial Data'!D18/'Financial Data'!D$10 | E18: ='Financial Data'!E18/'Financial Data'!E$10 | F18: ='Financial Data'!F18/'Financial Data'!F$10 | G18: ='Financial Data'!G18/'Financial Data'!G$10
A20: BALANCE SHEET - ASSETS | I20: Divide each balance sheet line by that year's Total Assets, locked the same way.
A21: Cash & Short-Term Investments | C21: ='Financial Data'!C21/'Financial Data'!C$29 | D21: ='Financial Data'!D21/'Financial Data'!D$29 | E21: ='Financial Data'!E21/'Financial Data'!E$29 | F21: ='Financial Data'!F21/'Financial Data'!F$29 | G21: ='Financial Data'!G21/'Financial Data'!G$29
A22: Accounts Receivable | C22: ='Financial Data'!C22/'Financial Data'!C$29 | D22: ='Financial Data'!D22/'Financial Data'!D$29 | E22: ='Financial Data'!E22/'Financial Data'!E$29 | F22: ='Financial Data'!F22/'Financial Data'!F$29 | G22: ='Financial Data'!G22/'Financial Data'!G$29
A23: Inventory | C23: ='Financial Data'!C23/'Financial Data'!C$29 | D23: ='Financial Data'!D23/'Financial Data'!D$29 | E23: ='Financial Data'!E23/'Financial Data'!E$29 | F23: ='Financial Data'!F23/'Financial Data'!F$29 | G23: ='Financial Data'!G23/'Financial Data'!G$29
A24: Other Current Assets | C24: ='Financial Data'!C24/'Financial Data'!C$29 | D24: ='Financial Data'!D24/'Financial Data'!D$29 | E24: ='Financial Data'!E24/'Financial Data'!E$29 | F24: ='Financial Data'!F24/'Financial Data'!F$29 | G24: ='Financial Data'!G24/'Financial Data'!G$29
A25: Total Current Assets | C25: ='Financial Data'!C25/'Financial Data'!C$29 | D25: ='Financial Data'!D25/'Financial Data'!D$29 | E25: ='Financial Data'!E25/'Financial Data'!E$29 | F25: ='Financial Data'!F25/'Financial Data'!F$29 | G25: ='Financial Data'!G25/'Financial Data'!G$29
A26: Property, Plant & Equipment (net) | C26: ='Financial Data'!C26/'Financial Data'!C$29 | D26: ='Financial Data'!D26/'Financial Data'!D$29 | E26: ='Financial Data'!E26/'Financial Data'!E$29 | F26: ='Financial Data'!F26/'Financial Data'!F$29 | G26: ='Financial Data'!G26/'Financial Data'!G$29
A27: Goodwill & Intangible Assets | C27: ='Financial Data'!C27/'Financial Data'!C$29 | D27: ='Financial Data'!D27/'Financial Data'!D$29 | E27: ='Financial Data'!E27/'Financial Data'!E$29 | F27: ='Financial Data'!F27/'Financial Data'!F$29 | G27: ='Financial Data'!G27/'Financial Data'!G$29
A28: Other Long-Term Assets | C28: ='Financial Data'!C28/'Financial Data'!C$29 | D28: ='Financial Data'!D28/'Financial Data'!D$29 | E28: ='Financial Data'!E28/'Financial Data'!E$29 | F28: ='Financial Data'!F28/'Financial Data'!F$29 | G28: ='Financial Data'!G28/'Financial Data'!G$29
A29: Total Assets | C29: ='Financial Data'!C29/'Financial Data'!C$29 | D29: ='Financial Data'!D29/'Financial Data'!D$29 | E29: ='Financial Data'!E29/'Financial Data'!E$29 | F29: ='Financial Data'!F29/'Financial Data'!F$29 | G29: ='Financial Data'!G29/'Financial Data'!G$29
A31: BALANCE SHEET - LIABILITIES & EQUITY
A32: Accounts Payable | C32: ='Financial Data'!C32/'Financial Data'!C$29 | D32: ='Financial Data'!D32/'Financial Data'!D$29 | E32: ='Financial Data'!E32/'Financial Data'!E$29 | F32: ='Financial Data'!F32/'Financial Data'!F$29 | G32: ='Financial Data'!G32/'Financial Data'!G$29
A33: Short-Term Debt & Current Portion of LTD | C33: ='Financial Data'!C33/'Financial Data'!C$29 | D33: ='Financial Data'!D33/'Financial Data'!D$29 | E33: ='Financial Data'!E33/'Financial Data'!E$29 | F33: ='Financial Data'!F33/'Financial Data'!F$29 | G33: ='Financial Data'!G33/'Financial Data'!G$29
A34: Other Current Liabilities | C34: ='Financial Data'!C34/'Financial Data'!C$29 | D34: ='Financial Data'!D34/'Financial Data'!D$29 | E34: ='Financial Data'!E34/'Financial Data'!E$29 | F34: ='Financial Data'!F34/'Financial Data'!F$29 | G34: ='Financial Data'!G34/'Financial Data'!G$29
A35: Total Current Liabilities | C35: ='Financial Data'!C35/'Financial Data'!C$29 | D35: ='Financial Data'!D35/'Financial Data'!D$29 | E35: ='Financial Data'!E35/'Financial Data'!E$29 | F35: ='Financial Data'!F35/'Financial Data'!F$29 | G35: ='Financial Data'!G35/'Financial Data'!G$29
A36: Long-Term Debt | C36: ='Financial Data'!C36/'Financial Data'!C$29 | D36: ='Financial Data'!D36/'Financial Data'!D$29 | E36: ='Financial Data'!E36/'Financial Data'!E$29 | F36: ='Financial Data'!F36/'Financial Data'!F$29 | G36: ='Financial Data'!G36/'Financial Data'!G$29
A37: Other Long-Term Liabilities | C37: ='Financial Data'!C37/'Financial Data'!C$29 | D37: ='Financial Data'!D37/'Financial Data'!D$29 | E37: ='Financial Data'!E37/'Financial Data'!E$29 | F37: ='Financial Data'!F37/'Financial Data'!F$29 | G37: ='Financial Data'!G37/'Financial Data'!G$29
A38: Total Liabilities | C38: ='Financial Data'!C38/'Financial Data'!C$29 | D38: ='Financial Data'!D38/'Financial Data'!D$29 | E38: ='Financial Data'!E38/'Financial Data'!E$29 | F38: ='Financial Data'!F38/'Financial Data'!F$29 | G38: ='Financial Data'!G38/'Financial Data'!G$29
A39: Total Shareholders' Equity | C39: ='Financial Data'!C39/'Financial Data'!C$29 | D39: ='Financial Data'!D39/'Financial Data'!D$29 | E39: ='Financial Data'!E39/'Financial Data'!E$29 | F39: ='Financial Data'!F39/'Financial Data'!F$29 | G39: ='Financial Data'!G39/'Financial Data'!G$29

Sheet Trend
A1: Trend Analysis
A2: How each line moved over five years - first year over year, then indexed to your earliest year.
A4: PART 1 - Percent change from the prior year
A5: Fiscal Year | C5: base year | D5: ='Financial Data'!D8 | E5: ='Financial Data'!E8 | F5: ='Financial Data'!F8 | G5: ='Financial Data'!G8
A6: Revenue (Net Sales) | D6: =('Financial Data'!D10-'Financial Data'!C10)/'Financial Data'!C10 | E6: =('Financial Data'!E10-'Financial Data'!D10)/'Financial Data'!D10 | F6: =('Financial Data'!F10-'Financial Data'!E10)/'Financial Data'!E10 | G6: =('Financial Data'!G10-'Financial Data'!F10)/'Financial Data'!F10 | I6: (This year - Last year) / Last year. There is no percent change for your earliest year because there is nothing before it.
A7: Cost of Revenue (COGS) | D7: =('Financial Data'!D11-'Financial Data'!C11)/'Financial Data'!C11 | E7: =('Financial Data'!E11-'Financial Data'!D11)/'Financial Data'!D11 | F7: =('Financial Data'!F11-'Financial Data'!E11)/'Financial Data'!E11 | G7: =('Financial Data'!G11-'Financial Data'!F11)/'Financial Data'!F11
A8: Gross Profit | D8: =('Financial Data'!D12-'Financial Data'!C12)/'Financial Data'!C12 | E8: =('Financial Data'!E12-'Financial Data'!D12)/'Financial Data'!D12 | F8: =('Financial Data'!F12-'Financial Data'!E12)/'Financial Data'!E12 | G8: =('Financial Data'!G12-'Financial Data'!F12)/'Financial Data'!F12
A9: Operating Income (EBIT) | D9: =('Financial Data'!D14-'Financial Data'!C14)/'Financial Data'!C14 | E9: =('Financial Data'!E14-'Financial Data'!D14)/'Financial Data'!D14 | F9: =('Financial Data'!F14-'Financial Data'!E14)/'Financial Data'!E14 | G9: =('Financial Data'!G14-'Financial Data'!F14)/'Financial Data'!F14
A10: Net Income | D10: =('Financial Data'!D18-'Financial Data'!C18)/'Financial Data'!C18 | E10: =('Financial Data'!E18-'Financial Data'!D18)/'Financial Data'!D18 | F10: =('Financial Data'!F18-'Financial Data'!E18)/'Financial Data'!E18 | G10: =('Financial Data'!G18-'Financial Data'!F18)/'Financial Data'!F18
A11: Inventory | D11: =('Financial Data'!D23-'Financial Data'!C23)/'Financial Data'!C23 | E11: =('Financial Data'!E23-'Financial Data'!D23)/'Financial Data'!D23 | F11: =('Financial Data'!F23-'Financial Data'!E23)/'Financial Data'!E23 | G11: =('Financial Data'!G23-'Financial Data'!F23)/'Financial Data'!F23
A12: Total Current Assets | D12: =('Financial Data'!D25-'Financial Data'!C25)/'Financial Data'!C25 | E12: =('Financial Data'!E25-'Financial Data'!D25)/'Financial Data'!D25 | F12: =('Financial Data'!F25-'Financial Data'!E25)/'Financial Data'!E25 | G12: =('Financial Data'!G25-'Financial Data'!F25)/'Financial Data'!F25
A13: Total Assets | D13: =('Financial Data'!D29-'Financial Data'!C29)/'Financial Data'!C29 | E13: =('Financial Data'!E29-'Financial Data'!D29)/'Financial Data'!D29 | F13: =('Financial Data'!F29-'Financial Data'!E29)/'Financial Data'!E29 | G13: =('Financial Data'!G29-'Financial Data'!F29)/'Financial Data'!F29
A14: Total Liabilities | D14: =('Financial Data'!D38-'Financial Data'!C38)/'Financial Data'!C38 | E14: =('Financial Data'!E38-'Financial Data'!D38)/'Financial Data'!D38 | F14: =('Financial Data'!F38-'Financial Data'!E38)/'Financial Data'!E38 | G14: =('Financial Data'!G38-'Financial Data'!F38)/'Financial Data'!F38
A15: Total Shareholders' Equity | D15: =('Financial Data'!D39-'Financial Data'!C39)/'Financial Data'!C39 | E15: =('Financial Data'!E39-'Financial Data'!D39)/'Financial Data'!D39 | F15: =('Financial Data'!F39-'Financial Data'!E39)/'Financial Data'!E39 | G15: =('Financial Data'!G39-'Financial Data'!F39)/'Financial Data'!F39
A18: PART 2 - Indexed to your earliest year (base = 100)
A19: Fiscal Year | C19: ='Financial Data'!C8 | D19: ='Financial Data'!D8 | E19: ='Financial Data'!E8 | F19: ='Financial Data'!F8 | G19: ='Financial Data'!G8
A20: Revenue (Net Sales) | C20: ='Financial Data'!C10/'Financial Data'!$C$10*100 | D20: ='Financial Data'!D10/'Financial Data'!$C$10*100 | E20: ='Financial Data'!E10/'Financial Data'!$C$10*100 | F20: ='Financial Data'!F10/'Financial Data'!$C$10*100 | G20: ='Financial Data'!G10/'Financial Data'!$C$10*100 | I20: Year N / earliest year x 100. Your earliest year will come out to exactly 100.0 - that is the check that you did it right. Lock the base year column with $.
A21: Cost of Revenue (COGS) | C21: ='Financial Data'!C11/'Financial Data'!$C$11*100 | D21: ='Financial Data'!D11/'Financial Data'!$C$11*100 | E21: ='Financial Data'!E11/'Financial Data'!$C$11*100 | F21: ='Financial Data'!F11/'Financial Data'!$C$11*100 | G21: ='Financial Data'!G11/'Financial Data'!$C$11*100
A22: Gross Profit | C22: ='Financial Data'!C12/'Financial Data'!$C$12*100 | D22: ='Financial Data'!D12/'Financial Data'!$C$12*100 | E22: ='Financial Data'!E12/'Financial Data'!$C$12*100 | F22: ='Financial Data'!F12/'Financial Data'!$C$12*100 | G22: ='Financial Data'!G12/'Financial Data'!$C$12*100
A23: Operating Income (EBIT) | C23: ='Financial Data'!C14/'Financial Data'!$C$14*100 | D23: ='Financial Data'!D14/'Financial Data'!$C$14*100 | E23: ='Financial Data'!E14/'Financial Data'!$C$14*100 | F23: ='Financial Data'!F14/'Financial Data'!$C$14*100 | G23: ='Financial Data'!G14/'Financial Data'!$C$14*100
A24: Net Income | C24: ='Financial Data'!C18/'Financial Data'!$C$18*100 | D24: ='Financial Data'!D18/'Financial Data'!$C$18*100 | E24: ='Financial Data'!E18/'Financial Data'!$C$18*100 | F24: ='Financial Data'!F18/'Financial Data'!$C$18*100 | G24: ='Financial Data'!G18/'Financial Data'!$C$18*100
A25: Inventory | C25: ='Financial Data'!C23/'Financial Data'!$C$23*100 | D25: ='Financial Data'!D23/'Financial Data'!$C$23*100 | E25: ='Financial Data'!E23/'Financial Data'!$C$23*100 | F25: ='Financial Data'!F23/'Financial Data'!$C$23*100 | G25: ='Financial Data'!G23/'Financial Data'!$C$23*100
A26: Total Current Assets | C26: ='Financial Data'!C25/'Financial Data'!$C$25*100 | D26: ='Financial Data'!D25/'Financial Data'!$C$25*100 | E26: ='Financial Data'!E25/'Financial Data'!$C$25*100 | F26: ='Financial Data'!F25/'Financial Data'!$C$25*100 | G26: ='Financial Data'!G25/'Financial Data'!$C$25*100
A27: Total Assets | C27: ='Financial Data'!C29/'Financial Data'!$C$29*100 | D27: ='Financial Data'!D29/'Financial Data'!$C$29*100 | E27: ='Financial Data'!E29/'Financial Data'!$C$29*100 | F27: ='Financial Data'!F29/'Financial Data'!$C$29*100 | G27: ='Financial Data'!G29/'Financial Data'!$C$29*100
A28: Total Liabilities | C28: ='Financial Data'!C38/'Financial Data'!$C$38*100 | D28: ='Financial Data'!D38/'Financial Data'!$C$38*100 | E28: ='Financial Data'!E38/'Financial Data'!$C$38*100 | F28: ='Financial Data'!F38/'Financial Data'!$C$38*100 | G28: ='Financial Data'!G38/'Financial Data'!$C$38*100
A29: Total Shareholders' Equity | C29: ='Financial Data'!C39/'Financial Data'!$C$39*100 | D29: ='Financial Data'!D39/'Financial Data'!$C$39*100 | E29: ='Financial Data'!E39/'Financial Data'!$C$39*100 | F29: ='Financial Data'!F39/'Financial Data'!$C$39*100 | G29: ='Financial Data'!G39/'Financial Data'!$C$39*100

Sheet Ratios
A1: Ratio Analysis
A2: Fourteen ratios, all five years, plus the DuPont decomposition.
A8: Fiscal Year | C8: ='Financial Data'!C8 | D8: ='Financial Data'!D8 | E8: ='Financial Data'!E8 | F8: ='Financial Data'!F8 | G8: ='Financial Data'!G8
A9: LIQUIDITY
A10: Current Ratio | C10: ='Financial Data'!C25/'Financial Data'!C35 | D10: ='Financial Data'!D25/'Financial Data'!D35 | E10: ='Financial Data'!E25/'Financial Data'!E35 | F10: ='Financial Data'!F25/'Financial Data'!F35 | G10: ='Financial Data'!G25/'Financial Data'!G35 | I10: Total Current Assets / Total Current Liabilities
A11: Quick Ratio | C11: =('Financial Data'!C25-'Financial Data'!C23)/'Financial Data'!C35 | D11: =('Financial Data'!D25-'Financial Data'!D23)/'Financial Data'!D35 | E11: =('Financial Data'!E25-'Financial Data'!E23)/'Financial Data'!E35 | F11: =('Financial Data'!F25-'Financial Data'!F23)/'Financial Data'!F35 | G11: =('Financial Data'!G25-'Financial Data'!G23)/'Financial Data'!G35 | I11: (Total Current Assets - Inventory) / Total Current Liabilities
A12: Cash Ratio | C12: ='Financial Data'!C21/'Financial Data'!C35 | D12: ='Financial Data'!D21/'Financial Data'!D35 | E12: ='Financial Data'!E21/'Financial Data'!E35 | F12: ='Financial Data'!F21/'Financial Data'!F35 | G12: ='Financial Data'!G21/'Financial Data'!G35 | I12: Cash & Short-Term Investments / Total Current Liabilities
A14: LEVERAGE
A15: Debt Ratio | C15: ='Financial Data'!C38/'Financial Data'!C29 | D15: ='Financial Data'!D38/'Financial Data'!D29 | E15: ='Financial Data'!E38/'Financial Data'!E29 | F15: ='Financial Data'!F38/'Financial Data'!F29 | G15: ='Financial Data'!G38/'Financial Data'!G29 | I15: Total Liabilities / Total Assets
A16: Debt-to-Equity | C16: ='Financial Data'!C38/'Financial Data'!C39 | D16: ='Financial Data'!D38/'Financial Data'!D39 | E16: ='Financial Data'!E38/'Financial Data'!E39 | F16: ='Financial Data'!F38/'Financial Data'!F39 | G16: ='Financial Data'!G38/'Financial Data'!G39 | I16: Total Liabilities / Total Shareholders' Equity
A17: Equity Multiplier | C17: ='Financial Data'!C29/'Financial Data'!C39 | D17: ='Financial Data'!D29/'Financial Data'!D39 | E17: ='Financial Data'!E29/'Financial Data'!E39 | F17: ='Financial Data'!F29/'Financial Data'!F39 | G17: ='Financial Data'!G29/'Financial Data'!G39 | I17: Total Assets / Total Shareholders' Equity
A18: Times Interest Earned | C18: ='Financial Data'!C14/'Financial Data'!C15 | D18: ='Financial Data'!D14/'Financial Data'!D15 | E18: ='Financial Data'!E14/'Financial Data'!E15 | F18: ='Financial Data'!F14/'Financial Data'!F15 | G18: ='Financial Data'!G14/'Financial Data'!G15 | I18: Operating Income (EBIT) / Interest Expense
A20: PROFITABILITY
A21: Gross Margin | C21: ='Financial Data'!C12/'Financial Data'!C10 | D21: ='Financial Data'!D12/'Financial Data'!D10 | E21: ='Financial Data'!E12/'Financial Data'!E10 | F21: ='Financial Data'!F12/'Financial Data'!F10 | G21: ='Financial Data'!G12/'Financial Data'!G10 | I21: Gross Profit / Revenue
A22: Operating Margin | C22: ='Financial Data'!C14/'Financial Data'!C10 | D22: ='Financial Data'!D14/'Financial Data'!D10 | E22: ='Financial Data'!E14/'Financial Data'!E10 | F22: ='Financial Data'!F14/'Financial Data'!F10 | G22: ='Financial Data'!G14/'Financial Data'!G10 | I22: Operating Income (EBIT) / Revenue
A23: Net Profit Margin | C23: ='Financial Data'!C18/'Financial Data'!C10 | D23: ='Financial Data'!D18/'Financial Data'!D10 | E23: ='Financial Data'!E18/'Financial Data'!E10 | F23: ='Financial Data'!F18/'Financial Data'!F10 | G23: ='Financial Data'!G18/'Financial Data'!G10 | I23: Net Income / Revenue
A24: Return on Assets (ROA) | C24: ='Financial Data'!C18/'Financial Data'!C29 | D24: ='Financial Data'!D18/'Financial Data'!D29 | E24: ='Financial Data'!E18/'Financial Data'!E29 | F24: ='Financial Data'!F18/'Financial Data'!F29 | G24: ='Financial Data'!G18/'Financial Data'!G29 | I24: Net Income / Total Assets
A25: Return on Equity (ROE) | C25: ='Financial Data'!C18/'Financial Data'!C39 | D25: ='Financial Data'!D18/'Financial Data'!D39 | E25: ='Financial Data'!E18/'Financial Data'!E39 | F25: ='Financial Data'!F18/'Financial Data'!F39 | G25: ='Financial Data'!G18/'Financial Data'!G39 | I25: Net Income / Total Shareholders' Equity
A27: EFFICIENCY
A28: Inventory Turnover | C28: ='Financial Data'!C11/'Financial Data'!C23 | D28: ='Financial Data'!D11/'Financial Data'!D23 | E28: ='Financial Data'!E11/'Financial Data'!E23 | F28: ='Financial Data'!F11/'Financial Data'!F23 | G28: ='Financial Data'!G11/'Financial Data'!G23 | I28: Cost of Revenue (COGS) / Inventory
A29: Total Asset Turnover | C29: ='Financial Data'!C10/'Financial Data'!C29 | D29: ='Financial Data'!D10/'Financial Data'!D29 | E29: ='Financial Data'!E10/'Financial Data'!E29 | F29: ='Financial Data'!F10/'Financial Data'!F29 | G29: ='Financial Data'!G10/'Financial Data'!G29 | I29: Revenue / Total Assets
A31: DUPONT DECOMPOSITION - ROE = Net Profit Margin x Total Asset Turnover x Equity Multiplier
A32: Fiscal Year | C32: ='Financial Data'!C8 | D32: ='Financial Data'!D8 | E32: ='Financial Data'!E8 | F32: ='Financial Data'!F8 | G32: ='Financial Data'!G8
A33: Net Profit Margin | C33: =C23 | D33: =D23 | E33: =E23 | F33: =F23 | G33: =G23 | I33: pull it from the Profitability block above
A34: x Total Asset Turnover | C34: =C29 | D34: =D29 | E34: =E29 | F34: =F29 | G34: =G29 | I34: pull it from the Efficiency block above
A35: x Equity Multiplier | C35: =C17 | D35: =D17 | E35: =E17 | F35: =F17 | G35: =G17 | I35: pull it from the Leverage block above
A36: =ROE (from DuPont) | C36: =C33*C34*C35 | D36: =D33*D34*D35 | E36: =E33*E34*E35 | F36: =F33*F34*F35 | G36: =G33*G34*G35 | I36: multiply the three rows above
A37: ROE (from Profitability block) | C37: =C25 | D37: =D25 | E37: =E25 | F37: =F25 | G37: =G25 | I37: link to the ROE row above
A38: CHECK: difference | C38: =C36-C37 | D38: =D36-D37 | E38: =E36-E37 | F38: =F36-F37 | G38: =G36-G37 | I38: the two ROE rows minus each other - must be 0.00%
A40: If the CHECK row is not zero, one of the three components is wrong. That is the point of the check - it catches your error before I do.
