Workbook

Sheet START HERE
A1: Financial Statement Analysis
A2: Generated by edgar-query. The Financial Data sheet is filled from SEC EDGAR. Every other sheet is yours to build.
A5: What you are building
A6: One company. Five fiscal years. The statements are already in front of you. What you build is the analysis: common-size statements, a trend analysis, and a set of ratios.
A8: Colour code
A9: Yellow cells = you type the number in.
A10: Green cells = you write the formula.
A13: The sheets, in order
A14: Financial Data - Already filled from SEC EDGAR. Read it, check it, but do not retype it.
A15: Common-Size - Every income statement line as a % of Revenue. Every balance sheet line as a % of Total Assets.
A16: Trend - Percent change from one year to the next, plus an indexed view with your earliest year as the base.
A17: Ratios - Fifteen ratios plus the DuPont decomposition.
... A43: [ ] You have not left the TTM column in by mistake

Sheet Financial Data
A1: Financial Data - type your five years here
A2: This is the only sheet where you type numbers. Everything else links back to it.
A3: Company name | I3: Oldest year on the left, most recent on the right. Keep that order everywhere.
A4: Ticker symbol
A5: Units (e.g. millions USD)
A6: Data source (paste the URL)
A8: Fiscal Year
A9: INCOME STATEMENT
A10: Revenue (Net Sales)
A11: Cost of Revenue (COGS)
A12: Gross Profit
A13: Operating Expenses
A14: Operating Income (EBIT)
A15: Interest Expense
A16: Pretax Income
... A39: Total Shareholders' Equity
A41: CHECK: Assets - (Liabilities + Equity) | C41: =IF(COUNT(C29,C38,C39)<3,"",C29-(C38+C39)) | D41: =IF(COUNT(D29,D38,D39)<3,"",D29-(D38+D39)) | E41: =IF(COUNT(E29,E38,E39)<3,"",E29-(E38+E39)) | F41: =IF(COUNT(F29,F38,F39)<3,"",F29-(F38+F39)) | G41: =IF(COUNT(G29,G38,G39)<3,"",G29-(G38+G39)) | I41: Should be within about 1.0 of zero in every year. Published figures are rounded, so a few tenths is normal. A number in the tens or hundreds means a typo above, or a line item you left out.

Sheet Common-Size
A1: Common-Size Statements
A2: Income statement as a % of Revenue. Balance sheet as a % of Total Assets.
A8: Fiscal Year | C8: ='Financial Data'!C8 | D8: ='Financial Data'!D8 | E8: ='Financial Data'!E8 | F8: ='Financial Data'!F8 | G8: ='Financial Data'!G8
A9: INCOME STATEMENT | I9: Divide each income statement line by that year's Revenue. Lock the Revenue row with $ so you can drag the formula down: ='Financial Data'!C10/'Financial Data'!C$10
A10: Revenue (Net Sales)
A11: Cost of Revenue (COGS)
A12: Gross Profit
A13: Operating Expenses
A14: Operating Income (EBIT)
A15: Interest Expense
A16: Pretax Income
A17: Income Tax Expense
A18: Net Income
A20: BALANCE SHEET - ASSETS | I20: Divide each balance sheet line by that year's Total Assets, locked the same way.
A21: Cash & Short-Term Investments
A22: Accounts Receivable
A23: Inventory
A24: Other Current Assets
A25: Total Current Assets
A26: Property, Plant & Equipment (net)
A27: Goodwill & Intangible Assets
A28: Other Long-Term Assets
A29: Total Assets
A31: BALANCE SHEET - LIABILITIES & EQUITY
A32: Accounts Payable
A33: Short-Term Debt & Current Portion of LTD
... A39: Total Shareholders' Equity

Sheet Trend
A1: Trend Analysis
A2: How each line moved over five years - first year over year, then indexed to your earliest year.
A4: PART 1 - Percent change from the prior year
A5: Fiscal Year | C5: base year | D5: ='Financial Data'!D8 | E5: ='Financial Data'!E8 | F5: ='Financial Data'!F8 | G5: ='Financial Data'!G8
A6: Revenue (Net Sales) | I6: (This year - Last year) / Last year. There is no percent change for your earliest year because there is nothing before it.
A7: Cost of Revenue (COGS)
A8: Gross Profit
A9: Operating Income (EBIT)
A10: Net Income
A11: Inventory
A12: Total Current Assets
A13: Total Assets
A14: Total Liabilities
A15: Total Shareholders' Equity
A18: PART 2 - Indexed to your earliest year (base = 100)
A19: Fiscal Year | C19: ='Financial Data'!C8 | D19: ='Financial Data'!D8 | E19: ='Financial Data'!E8 | F19: ='Financial Data'!F8 | G19: ='Financial Data'!G8
A20: Revenue (Net Sales) | I20: Year N / earliest year x 100. Your earliest year will come out to exactly 100.0 - that is the check that you did it right. Lock the base year column with $.
A21: Cost of Revenue (COGS)
A22: Gross Profit
A23: Operating Income (EBIT)
A24: Net Income
A25: Inventory
A26: Total Current Assets
A27: Total Assets
A28: Total Liabilities
A29: Total Shareholders' Equity

Sheet Ratios
A1: Ratio Analysis
A2: Fourteen ratios, all five years, plus the DuPont decomposition.
A8: Fiscal Year | C8: ='Financial Data'!C8 | D8: ='Financial Data'!D8 | E8: ='Financial Data'!E8 | F8: ='Financial Data'!F8 | G8: ='Financial Data'!G8
A9: LIQUIDITY
A10: Current Ratio | I10: Total Current Assets / Total Current Liabilities
A11: Quick Ratio | I11: (Total Current Assets - Inventory) / Total Current Liabilities
A12: Cash Ratio | I12: Cash & Short-Term Investments / Total Current Liabilities
A14: LEVERAGE
A15: Debt Ratio | I15: Total Liabilities / Total Assets
A16: Debt-to-Equity | I16: Total Liabilities / Total Shareholders' Equity
A17: Equity Multiplier | I17: Total Assets / Total Shareholders' Equity
A18: Times Interest Earned | I18: Operating Income (EBIT) / Interest Expense
A20: PROFITABILITY
A21: Gross Margin | I21: Gross Profit / Revenue
A22: Operating Margin | I22: Operating Income (EBIT) / Revenue
A23: Net Profit Margin | I23: Net Income / Revenue
A24: Return on Assets (ROA) | I24: Net Income / Total Assets
A25: Return on Equity (ROE) | I25: Net Income / Total Shareholders' Equity
A27: EFFICIENCY
A28: Inventory Turnover | I28: Cost of Revenue (COGS) / Inventory
A29: Total Asset Turnover | I29: Revenue / Total Assets
A31: DUPONT DECOMPOSITION - ROE = Net Profit Margin x Total Asset Turnover x Equity Multiplier
A32: Fiscal Year | C32: ='Financial Data'!C8 | D32: ='Financial Data'!D8 | E32: ='Financial Data'!E8 | F32: ='Financial Data'!F8 | G32: ='Financial Data'!G8
A33: Net Profit Margin | I33: pull it from the Profitability block above
A34: x Total Asset Turnover | I34: pull it from the Efficiency block above
A35: x Equity Multiplier | I35: pull it from the Leverage block above
A36: =ROE (from DuPont) | I36: multiply the three rows above
A37: ROE (from Profitability block) | I37: link to the ROE row above
A38: CHECK: difference | I38: the two ROE rows minus each other - must be 0.00%
A40: If the CHECK row is not zero, one of the three components is wrong. That is the point of the check - it catches your error before I do.
